<?xml version="1.0" encoding="utf-8"?>
<dicta xmlns="http://www.sibawayhi.org/schema/2024/05/igt" bab="122">
   <dictum id="١٨٧٤١">
      <text>
         <ar>هٰذَا أَبُو الْحَاْرِثِ</ar>
         <free/>
      </text>
      <igt>
         <t>
            <ar>هٰذَا</ar>
         </t>
         <t>
            <ar>أَبُو</ar>
         </t>
         <t>
            <ar>الْحَاْرِثِ</ar>
         </t>
      </igt>
   </dictum>
   <dictum id="١٥٣٧٨">
      <text>
         <ar>هٰذَا ثُعَاْلَةُ</ar>
         <free/>
      </text>
      <igt>
         <t>
            <ar>هٰذَا</ar>
         </t>
         <t>
            <ar>ثُعَاْلَةُ</ar>
         </t>
      </igt>
   </dictum>
   <dictum id="٠٢٨٠٨">
      <text>
         <ar>هٰذَا الْأَسَدُ</ar>
         <free/>
      </text>
      <igt>
         <t>
            <ar>هٰذَا</ar>
         </t>
         <t>
            <ar>الْأَسَدُ</ar>
         </t>
      </igt>
   </dictum>
   <dictum id="٣٣٧٠٦">
      <text>
         <ar>هٰذَا الثَّعْلَبُ</ar>
         <free/>
      </text>
      <igt>
         <t>
            <ar>هٰذَا</ar>
         </t>
         <t>
            <ar>الثَّعْلَبُ</ar>
         </t>
      </igt>
   </dictum>
   <dictum id="٠٤٣٩٤">
      <text>
         <ar>هٰذَا زَيْدٌ</ar>
         <free/>
      </text>
      <igt>
         <t>
            <ar>هٰذَا</ar>
         </t>
         <t>
            <ar>زَيْدٌ</ar>
         </t>
      </igt>
   </dictum>
   <dictum id="٢٣٣٣٧">
      <text>
         <ar>هٰذَا الرَّجُلُ</ar>
         <free/>
      </text>
      <igt>
         <t>
            <ar>هٰذَا</ar>
         </t>
         <t>
            <ar>الرَّجُلُ</ar>
         </t>
      </igt>
   </dictum>
   <dictum id="٥٥٧٤٨">
      <text>
         <ar>هٰذَا زَيْدٌ</ar>
         <free/>
      </text>
      <igt>
         <t>
            <ar>هٰذَا</ar>
         </t>
         <t>
            <ar>زَيْدٌ</ar>
         </t>
      </igt>
   </dictum>
   <dictum id="٩٢٥٦٦">
      <text>
         <ar>هٰذَا الرَّجُلُ الَّذِي مِنْ حِلْيَتِهِ وَمِنْ أَمْرِهِ كَذَا وكَذَا بِعَيْنِهِ</ar>
         <free/>
      </text>
      <igt>
         <t>
            <ar>هٰذَا</ar>
         </t>
         <t>
            <ar>الرَّجُلُ</ar>
         </t>
         <t>
            <ar>الَّذِي</ar>
         </t>
         <t>
            <ar>مِنْ</ar>
         </t>
         <t>
            <ar>حِلْيَتِهِ</ar>
         </t>
         <t>
            <ar>وَمِنْ</ar>
         </t>
         <t>
            <ar>أَمْرِهِ</ar>
         </t>
         <t>
            <ar>كَذَا</ar>
         </t>
         <t>
            <ar>وكَذَا</ar>
         </t>
         <t>
            <ar>بِعَيْنِهِ</ar>
         </t>
      </igt>
   </dictum>
   <dictum id="١٥٣٢٦">
      <text>
         <ar>هٰذَا الرَّجُلُ</ar>
         <free/>
      </text>
      <igt>
         <t>
            <ar>هٰذَا</ar>
         </t>
         <t>
            <ar>الرَّجُلُ</ar>
         </t>
      </igt>
   </dictum>
   <dictum id="٢٥٩٥٢">
      <text>
         <ar>هٰذَا الرَّجُلُ</ar>
         <free/>
      </text>
      <igt>
         <t>
            <ar>هٰذَا</ar>
         </t>
         <t>
            <ar>الرَّجُلُ</ar>
         </t>
      </igt>
   </dictum>
   <dictum id="٤٥٣٦١">
      <text>
         <ar>زَيْدٌ</ar>
         <free/>
      </text>
      <igt>
         <t>
            <ar>زَيْدٌ</ar>
         </t>
      </igt>
   </dictum>
   <dictum id="٢١٤٩١">
      <text>
         <ar>هٰذَا أَبُو الْحَاْرِثِ</ar>
         <free/>
      </text>
      <igt>
         <t>
            <ar>هٰذَا</ar>
         </t>
         <t>
            <ar>أَبُو</ar>
         </t>
         <t>
            <ar>الْحَاْرِثِ</ar>
         </t>
      </igt>
   </dictum>
   <dictum id="٥٧٦٤٨">
      <text>
         <ar>هٰذَا الْأَسَدُ</ar>
         <free/>
      </text>
      <igt>
         <t>
            <ar>هٰذَا</ar>
         </t>
         <t>
            <ar>الْأَسَدُ</ar>
         </t>
      </igt>
   </dictum>
   <dictum id="٩٣٨٠٣">
      <text>
         <ar>هٰذَا الَّذِي سَمِعْتَ بِاسْمِهِ</ar>
         <free/>
      </text>
      <igt>
         <t>
            <ar>هٰذَا</ar>
         </t>
         <t>
            <ar>الَّذِي</ar>
         </t>
         <t>
            <ar>سَمِعْتَ</ar>
         </t>
         <t>
            <ar>بِاسْمِهِ</ar>
         </t>
      </igt>
   </dictum>
   <dictum id="٤١٦٦٩">
      <text>
         <ar>هٰذَا الَّذِي قَدْ عَرَفْتَ أَشْبَاْهَهُ</ar>
         <free/>
      </text>
      <igt>
         <t>
            <ar>هٰذَا</ar>
         </t>
         <t>
            <ar>الَّذِي</ar>
         </t>
         <t>
            <ar>قَدْ</ar>
         </t>
         <t>
            <ar>عَرَفْتَ</ar>
         </t>
         <t>
            <ar>أَشْبَاْهَهُ</ar>
         </t>
      </igt>
   </dictum>
   <dictum id="٧٦٨٦٨">
      <text>
         <ar>هٰذَا ابْنُ قِترَةَ</ar>
         <free/>
      </text>
      <igt>
         <t>
            <ar>هٰذَا</ar>
         </t>
         <t>
            <ar>ابْنُ</ar>
         </t>
         <t>
            <ar>قِترَةَ</ar>
         </t>
      </igt>
   </dictum>
   <dictum id="٤٣٦٠٦">
      <text>
         <ar>هٰذَا الْحَيَّةُ الَّذِي مِنْ أَمْرِهِ كَذَا وكَذَا</ar>
         <free/>
      </text>
      <igt>
         <t>
            <ar>هٰذَا</ar>
         </t>
         <t>
            <ar>الْحَيَّةُ</ar>
         </t>
         <t>
            <ar>الَّذِي</ar>
         </t>
         <t>
            <ar>مِنْ</ar>
         </t>
         <t>
            <ar>أَمْرِهِ</ar>
         </t>
         <t>
            <ar>كَذَا</ar>
         </t>
         <t>
            <ar>وكَذَا</ar>
         </t>
      </igt>
   </dictum>
   <dictum id="٣٥٥٨٣">
      <text>
         <ar>هٰذَا الضَّرْبُ الَّذِي مِنْ أَمْرِهِ كَذَا وكَذَا مِنَ الْكَمَأةِ</ar>
         <free/>
      </text>
      <igt>
         <t>
            <ar>هٰذَا</ar>
         </t>
         <t>
            <ar>الضَّرْبُ</ar>
         </t>
         <t>
            <ar>الَّذِي</ar>
         </t>
         <t>
            <ar>مِنْ</ar>
         </t>
         <t>
            <ar>أَمْرِهِ</ar>
         </t>
         <t>
            <ar>كَذَا</ar>
         </t>
         <t>
            <ar>وكَذَا</ar>
         </t>
         <t>
            <ar>مِنَ</ar>
         </t>
         <t>
            <ar>الْكَمَأةِ</ar>
         </t>
      </igt>
   </dictum>
   <dictum id="٢٩١٢٠">
      <text>
         <ar>هٰذَا الضَّرْبُ الَّذِي سَمِعْتَ بِهِ مِنَ الْجَنَاْدِبِ أَوْ رَأَيْتَهُ</ar>
         <free/>
      </text>
      <igt>
         <t>
            <ar>هٰذَا</ar>
         </t>
         <t>
            <ar>الضَّرْبُ</ar>
         </t>
         <t>
            <ar>الَّذِي</ar>
         </t>
         <t>
            <ar>سَمِعْتَ</ar>
         </t>
         <t>
            <ar>بِهِ</ar>
         </t>
         <t>
            <ar>مِنَ</ar>
         </t>
         <t>
            <ar>الْجَنَاْدِبِ</ar>
         </t>
         <t>
            <ar>أَوْ</ar>
         </t>
         <t>
            <ar>رَأَيْتَهُ</ar>
         </t>
      </igt>
   </dictum>
   <dictum id="٢٥٧٥٥">
      <text>
         <ar>هٰذَا الضَّرْبُ الَّذِي سَمِعْتَهُ أَوْ رَأَيْتَهُ مِنَ السِّبَاْعِ</ar>
         <free/>
      </text>
      <igt>
         <t>
            <ar>هٰذَا</ar>
         </t>
         <t>
            <ar>الضَّرْبُ</ar>
         </t>
         <t>
            <ar>الَّذِي</ar>
         </t>
         <t>
            <ar>سَمِعْتَهُ</ar>
         </t>
         <t>
            <ar>أَوْ</ar>
         </t>
         <t>
            <ar>رَأَيْتَهُ</ar>
         </t>
         <t>
            <ar>مِنَ</ar>
         </t>
         <t>
            <ar>السِّبَاْعِ</ar>
         </t>
      </igt>
   </dictum>
   <dictum id="٨٩٤٣٨">
      <text>
         <ar>فِي كُلِّ وَاْحِدٍ مِنْ هٰذَا الضَّرْبِ الَّذِي يُعْرَفُ مِنْ أَجْنَاْسِ الْأَرْضِ بِصُوْرَةِ كَذَا</ar>
         <free/>
      </text>
      <igt>
         <t>
            <ar>فِي</ar>
         </t>
         <t>
            <ar>كُلِّ</ar>
         </t>
         <t>
            <ar>وَاْحِدٍ</ar>
         </t>
         <t>
            <ar>مِنْ</ar>
         </t>
         <t>
            <ar>هٰذَا</ar>
         </t>
         <t>
            <ar>الضَّرْبِ</ar>
         </t>
         <t>
            <ar>الَّذِي</ar>
         </t>
         <t>
            <ar>يُعْرَفُ</ar>
         </t>
         <t>
            <ar>مِنْ</ar>
         </t>
         <t>
            <ar>أَجْنَاْسِ</ar>
         </t>
         <t>
            <ar>الْأَرْضِ</ar>
         </t>
         <t>
            <ar>بِصُوْرَةِ</ar>
         </t>
         <t>
            <ar>كَذَا</ar>
         </t>
      </igt>
   </dictum>
   <dictum id="٦٩٧٤١">
      <text>
         <ar>هٰذِهِ الَّتِي تُعْرَفُ مِنْ أَجْنَاْسِ الْأَرْضِ بِصُوْرَةِ كَذَا</ar>
         <free/>
      </text>
      <igt>
         <t>
            <ar>هٰذِهِ</ar>
         </t>
         <t>
            <ar>الَّتِي</ar>
         </t>
         <t>
            <ar>تُعْرَفُ</ar>
         </t>
         <t>
            <ar>مِنْ</ar>
         </t>
         <t>
            <ar>أَجْنَاْسِ</ar>
         </t>
         <t>
            <ar>الْأَرْضِ</ar>
         </t>
         <t>
            <ar>بِصُوْرَةِ</ar>
         </t>
         <t>
            <ar>كَذَا</ar>
         </t>
      </igt>
   </dictum>
   <dictum id="١٩٠١٩">
      <text>
         <ar>هٰذَا الرَّجُلُ</ar>
         <free/>
      </text>
      <igt>
         <t>
            <ar>هٰذَا</ar>
         </t>
         <t>
            <ar>الرَّجُلُ</ar>
         </t>
      </igt>
   </dictum>
   <dictum id="٣٠٢٤٤">
      <text>
         <ar>هٰذَا الرَّجُلُ قَاْئِمٌ</ar>
         <free/>
      </text>
      <igt>
         <t>
            <ar>هٰذَا</ar>
         </t>
         <t>
            <ar>الرَّجُلُ</ar>
         </t>
         <t>
            <ar>قَاْئِمٌ</ar>
         </t>
      </igt>
   </dictum>
   <dictum id="٥٣٥٢٩">
      <text>
         <ar>هٰذَا زَيْدٌ مُقْبِلٌ</ar>
         <free/>
      </text>
      <igt>
         <t>
            <ar>هٰذَا</ar>
         </t>
         <t>
            <ar>زَيْدٌ</ar>
         </t>
         <t>
            <ar>مُقْبِلٌ</ar>
         </t>
      </igt>
   </dictum>
   <dictum id="٩٣٧٠٤">
      <text>
         <ar>هٰذَا رَجُلٌ مُنْطَلِقٌ</ar>
         <free/>
      </text>
      <igt>
         <t>
            <ar>هٰذَا</ar>
         </t>
         <t>
            <ar>رَجُلٌ</ar>
         </t>
         <t>
            <ar>مُنْطَلِقٌ</ar>
         </t>
      </igt>
   </dictum>
   <dictum id="٢٨٩٤٣">
      <text>
         <ar>هٰذَا قَيْسُ قُفَّةٍ آخَرُ مُنْطَلِقٌ</ar>
         <free/>
      </text>
      <igt>
         <t>
            <ar>هٰذَا</ar>
         </t>
         <t>
            <ar>قَيْسُ</ar>
         </t>
         <t>
            <ar>قُفَّةٍ</ar>
         </t>
         <t>
            <ar>آخَرُ</ar>
         </t>
         <t>
            <ar>مُنْطَلِقٌ</ar>
         </t>
      </igt>
   </dictum>
   <dictum id="٧٥٤١٣">
      <text>
         <ar>هٰذَا عُثْمَاْنٌ آخَرُ</ar>
         <free/>
      </text>
      <igt>
         <t>
            <ar>هٰذَا</ar>
         </t>
         <t>
            <ar>عُثْمَاْنٌ</ar>
         </t>
         <t>
            <ar>آخَرُ</ar>
         </t>
      </igt>
   </dictum>
   <dictum id="٣٨٨٩٤">
      <text>
         <ar>هٰذَا زَيْدٌ مُنْطَلِقٌ</ar>
         <free/>
      </text>
      <igt>
         <t>
            <ar>هٰذَا</ar>
         </t>
         <t>
            <ar>زَيْدٌ</ar>
         </t>
         <t>
            <ar>مُنْطَلِقٌ</ar>
         </t>
      </igt>
   </dictum>
   <dictum id="١٣٠٨٩">
      <text>
         <ar>هٰذَا رَجُلٌ مُنْطَلِقٌ</ar>
         <free/>
      </text>
      <igt>
         <t>
            <ar>هٰذَا</ar>
         </t>
         <t>
            <ar>رَجُلٌ</ar>
         </t>
         <t>
            <ar>مُنْطَلِقٌ</ar>
         </t>
      </igt>
   </dictum>
   <dictum id="٣٤٢١٠">
      <text>
         <ar>هٰذَا أَحَمَرُ قُمُدٌّ</ar>
         <free/>
      </text>
      <igt>
         <t>
            <ar>هٰذَا</ar>
         </t>
         <t>
            <ar>أَحَمَرُ</ar>
         </t>
         <t>
            <ar>قُمُدٌّ</ar>
         </t>
      </igt>
   </dictum>
   <dictum id="١١٤٨١">
      <text>
         <ar>عَلَى أَوْلَاْدِ أَحْقَبَ صِيَاْمٍ</ar>
         <free/>
      </text>
      <igt>
         <t>
            <ar>عَلَى</ar>
         </t>
         <t>
            <ar>أَوْلَاْدِ</ar>
         </t>
         <t>
            <ar>أَحْقَبَ</ar>
         </t>
         <t>
            <ar>صِيَاْمٍ</ar>
         </t>
      </igt>
   </dictum>
</dicta>
